{
  "built_at": "2026-07-01T04:15:22.131Z",
  "note": "public_id for /v1/models and request model; maps to model_req_key",
  "account_snapshot": {
    "fetched_at": "2026-06-26T09:07:42.768Z",
    "image": [
      "high_aes_general_v50",
      "high_aes_general_v42",
      "high_aes_general_v40l"
    ],
    "video": [
      "dreamina_seedance_40_mini",
      "dreamina_seedance_40",
      "dreamina_seedance_40_pro",
      "dreamina_ic_generate_video_model_vgfm_3.5_pro",
      "dreamina_ic_generate_video_model_vgfm_3.0_pro",
      "dreamina_ic_generate_video_model_vgfm_3.0_fast"
    ]
  },
  "models": [
    {
      "public_id": "gpt-image-2",
      "model_req_key": "dreamina_lib_img_20260423",
      "model_type": "image",
      "display_name": "GPT Image 2",
      "model_name": "web_model_gpt_image_2_name",
      "model_tip": "web_model_gpt_image_2_desc",
      "feats": [
        "new_model",
        "default_scene",
        "t2i",
        "byte_edit",
        "simple_image",
        "etta",
        "byte_edit_with_empty_prompt",
        "byte_edit_with_custom_ratio",
        "refuse_image",
        "hide_custom_ratio",
        "gpt_image_model",
        "per_piece"
      ],
      "resolution_map": [
        "1k"
      ],
      "upstream_seen": true
    },
    {
      "public_id": "seedream-5.0-lite",
      "model_req_key": "high_aes_general_v50",
      "model_type": "image",
      "display_name": "Seedream 5.0 Lite",
      "model_name": "Image 5.0 Lite",
      "model_tip": "Prompt-based image creation with high precision.",
      "upstream_seen": true
    },
    {
      "public_id": "seedream-4.7",
      "model_req_key": "high_aes_general_v43",
      "model_type": "image",
      "display_name": "Seedream 4.7",
      "model_name": "Image 4.7",
      "model_tip": "Better quality, more accurate prompt understanding.",
      "feats": [
        "new_model",
        "default_scene",
        "t2i",
        "byte_edit",
        "refuse_image",
        "smart_scale",
        "per_piece",
        "think_then_draw",
        "byte_edit_with_empty_prompt",
        "byte_edit_with_custom_ratio",
        "etta",
        "support_subject"
      ],
      "resolution_map": [
        "2k",
        "4k"
      ],
      "upstream_seen": true
    },
    {
      "public_id": "seedream-4.6",
      "model_req_key": "high_aes_general_v42",
      "model_type": "image",
      "display_name": "Seedream 4.6",
      "model_name": "Image 4.6",
      "model_tip": "Improved character consistency. Efficient on credits.",
      "upstream_seen": true
    },
    {
      "public_id": "seedream-4.5",
      "model_req_key": "high_aes_general_v40l",
      "model_type": "image",
      "display_name": "Seedream 4.5",
      "model_name": "Image 4.5",
      "model_tip": "Reliable character and style consistency for every prompt.",
      "upstream_seen": true
    },
    {
      "public_id": "seedance-2.0-mini",
      "model_req_key": "dreamina_seedance_40_mini",
      "model_type": "video",
      "display_name": "Seedance 2.0 Mini",
      "model_name": "Dreamina Seedance 2.0 Mini",
      "model_tip": "Most cost-effective, quicker results. Real human faces are not supported.",
      "options": [
        "resolution",
        "unified_edit",
        "input_media_type",
        "frames",
        "fps",
        "video_aspect_ratio"
      ],
      "upstream_seen": true
    },
    {
      "public_id": "seedance-2.0-fast",
      "model_req_key": "dreamina_seedance_40",
      "model_type": "video",
      "display_name": "Seedance 2.0 Fast",
      "model_name": "Dreamina Seedance 2.0 Fast",
      "model_tip": "Fast generation, lower cost. Real human faces are not supported.",
      "options": [
        "resolution",
        "unified_edit",
        "input_media_type",
        "frames",
        "fps",
        "video_aspect_ratio"
      ],
      "upstream_seen": true
    },
    {
      "public_id": "seedance-2.0",
      "model_req_key": "dreamina_seedance_40_pro",
      "model_type": "video",
      "display_name": "Seedance 2.0",
      "model_name": "Dreamina Seedance 2.0",
      "model_tip": "Most versatile, director-level control. Real human faces are not supported.",
      "options": [
        "resolution",
        "unified_edit",
        "input_media_type",
        "frames",
        "fps",
        "video_aspect_ratio"
      ],
      "upstream_seen": true
    },
    {
      "public_id": "seedance-1.5-pro",
      "model_req_key": "dreamina_ic_generate_video_model_vgfm_3.5_pro",
      "model_type": "video",
      "display_name": "Seedance 1.5 Pro",
      "model_name": "Dreamina Seedance 1.5 Pro",
      "model_tip": "Generates videos with synced, natural sound.",
      "options": [
        "input_media_type",
        "resolution",
        "frames",
        "fps",
        "video_aspect_ratio"
      ],
      "upstream_seen": true
    },
    {
      "public_id": "seedance-1.0-fast",
      "model_req_key": "dreamina_ic_generate_video_model_vgfm_3.0_fast",
      "model_type": "video",
      "display_name": "Seedance 1.0 Fast",
      "model_name": "Dreamina Seedance 1.0 Fast",
      "model_tip": "Film-level performance, faster and more credit-efficient.",
      "options": [
        "multi_frames",
        "input_media_type",
        "resolution",
        "frames",
        "fps",
        "video_aspect_ratio"
      ],
      "upstream_seen": true
    },
    {
      "public_id": "seedance-1.0",
      "model_req_key": "dreamina_ic_generate_video_model_vgfm_3.0_pro",
      "model_type": "video",
      "display_name": "Seedance 1.0",
      "model_name": "Dreamina Seedance 1.0",
      "model_tip": "",
      "options": [
        "input_media_type",
        "resolution",
        "frames",
        "fps",
        "video_aspect_ratio"
      ],
      "upstream_seen": true
    }
  ]
}